moviessdk_Pricile/__init__.py
moviessdk_Pricile/movies_client.py
moviessdk_Pricile/movies_config.py
moviessdk_Pricile/schemas/__init__.py
moviessdk_Pricile/schemas/schemas.py
moviessdk_pricile-0.0.3.dist-info/METADATA
moviessdk_pricile-0.0.3.dist-info/WHEEL
moviessdk_pricile-0.0.3.dist-info/top_level.txt
moviessdk_pricile-0.0.3.dist-info/RECORD
