Metadata-Version: 2.4
Name: moviessdk_Pricile
Version: 0.0.3
Summary: Software Development Kit (SDK) for MovieLens API
Author: [Gaëlle Pricile GANGBE]
Classifier: Development Status :: 3 - Alpha
Classifier: Programming Language :: Python :: 3
Classifier: License :: OSI Approved :: MIT License
Classifier: Operating System :: OS Independent
Requires-Python: >=3.11
Requires-Dist: httpx>=0.28.1
Requires-Dist: pydantic>=2.11.2
Requires-Dist: backoff>=2.2.1
Requires-Dist: python-dotenv
